{
  "run_id": "baseline_actionable_sync_20260220T2310Z",
  "generated_at": "2026-02-21T02:07:34.233630+00:00",
  "totals": {
    "plugins": 200,
    "ok": 190,
    "error": 9,
    "running": 1,
    "degraded": 0,
    "aborted": 0
  },
  "priority_queue": [
    {
      "plugin_id": "analysis_control_chart_ewma",
      "status": "error",
      "reason": "runtime_failure",
      "duration_ms": 38275,
      "max_rss_kb": 2425172,
      "exit_code": 0,
      "priority_score": 3613447.0,
      "recommended_next_step": "Capture plugin-specific traceback, add guardrails, and force deterministic fallback result.",
      "rank": 1
    },
    {
      "plugin_id": "analysis_control_chart_cusum",
      "status": "error",
      "reason": "runtime_failure",
      "duration_ms": 35571,
      "max_rss_kb": 2424052,
      "exit_code": 0,
      "priority_score": 3609623.0,
      "recommended_next_step": "Capture plugin-specific traceback, add guardrails, and force deterministic fallback result.",
      "rank": 2
    },
    {
      "plugin_id": "analysis_control_chart_individuals",
      "status": "error",
      "reason": "runtime_failure",
      "duration_ms": 35023,
      "max_rss_kb": 2421104,
      "exit_code": 0,
      "priority_score": 3606127.0,
      "recommended_next_step": "Capture plugin-specific traceback, add guardrails, and force deterministic fallback result.",
      "rank": 3
    },
    {
      "plugin_id": "analysis_multivariate_control_charts",
      "status": "error",
      "reason": "runtime_failure",
      "duration_ms": 23936,
      "max_rss_kb": 2086008,
      "exit_code": 0,
      "priority_score": 3259944.0,
      "recommended_next_step": "Capture plugin-specific traceback, add guardrails, and force deterministic fallback result.",
      "rank": 4
    },
    {
      "plugin_id": "analysis_control_chart_suite",
      "status": "error",
      "reason": "runtime_failure",
      "duration_ms": 27341,
      "max_rss_kb": 1843080,
      "exit_code": 0,
      "priority_score": 3020421.0,
      "recommended_next_step": "Capture plugin-specific traceback, add guardrails, and force deterministic fallback result.",
      "rank": 5
    },
    {
      "plugin_id": "analysis_distribution_drift_suite",
      "status": "error",
      "reason": "runtime_failure",
      "duration_ms": 26716,
      "max_rss_kb": 1841884,
      "exit_code": 0,
      "priority_score": 3018600.0,
      "recommended_next_step": "Capture plugin-specific traceback, add guardrails, and force deterministic fallback result.",
      "rank": 6
    },
    {
      "plugin_id": "analysis_phate_trajectory_embedding_v1",
      "status": "error",
      "reason": "runtime_failure",
      "duration_ms": 28721,
      "max_rss_kb": 1754196,
      "exit_code": 0,
      "priority_score": 2932917.0,
      "recommended_next_step": "Capture plugin-specific traceback, add guardrails, and force deterministic fallback result.",
      "rank": 7
    },
    {
      "plugin_id": "analysis_conformance_alignments",
      "status": "ok",
      "reason": "high_duration_hotspot",
      "duration_ms": 581018,
      "max_rss_kb": 1638100,
      "exit_code": 0,
      "priority_score": 2289118.0,
      "recommended_next_step": "Add bounded-window execution path and lightweight approximation mode for large inputs.",
      "rank": 8
    },
    {
      "plugin_id": "analysis_markov_transition_shift",
      "status": "ok",
      "reason": "high_duration_hotspot",
      "duration_ms": 562130,
      "max_rss_kb": 1640448,
      "exit_code": 0,
      "priority_score": 2272578.0,
      "recommended_next_step": "Add bounded-window execution path and lightweight approximation mode for large inputs.",
      "rank": 9
    },
    {
      "plugin_id": "analysis_local_outlier_factor",
      "status": "ok",
      "reason": "high_memory_hotspot",
      "duration_ms": 263066,
      "max_rss_kb": 1640048,
      "exit_code": 0,
      "priority_score": 1963114.0,
      "recommended_next_step": "Stream/batch large computations and avoid materializing wide intermediate DataFrames.",
      "rank": 10
    },
    {
      "plugin_id": "analysis_close_cycle_start_backtrack_v1",
      "status": "ok",
      "reason": "high_memory_hotspot",
      "duration_ms": 197935,
      "max_rss_kb": 1541776,
      "exit_code": 0,
      "priority_score": 1799711.0,
      "recommended_next_step": "Stream/batch large computations and avoid materializing wide intermediate DataFrames.",
      "rank": 11
    },
    {
      "plugin_id": "analysis_actionable_ops_levers_v1",
      "status": "ok",
      "reason": "high_memory_hotspot",
      "duration_ms": 97974,
      "max_rss_kb": 1638304,
      "exit_code": 0,
      "priority_score": 1796278.0,
      "recommended_next_step": "Stream/batch large computations and avoid materializing wide intermediate DataFrames.",
      "rank": 12
    },
    {
      "plugin_id": "analysis_close_cycle_window_resolver",
      "status": "ok",
      "reason": "high_memory_hotspot",
      "duration_ms": 194279,
      "max_rss_kb": 1539816,
      "exit_code": 0,
      "priority_score": 1794095.0,
      "recommended_next_step": "Stream/batch large computations and avoid materializing wide intermediate DataFrames.",
      "rank": 13
    },
    {
      "plugin_id": "analysis_dynamic_close_detection",
      "status": "ok",
      "reason": "high_memory_hotspot",
      "duration_ms": 188061,
      "max_rss_kb": 1542364,
      "exit_code": 0,
      "priority_score": 1790425.0,
      "recommended_next_step": "Stream/batch large computations and avoid materializing wide intermediate DataFrames.",
      "rank": 14
    },
    {
      "plugin_id": "analysis_changepoint_energy_edivisive",
      "status": "ok",
      "reason": "high_memory_hotspot",
      "duration_ms": 86058,
      "max_rss_kb": 1637936,
      "exit_code": 0,
      "priority_score": 1783994.0,
      "recommended_next_step": "Stream/batch large computations and avoid materializing wide intermediate DataFrames.",
      "rank": 15
    },
    {
      "plugin_id": "analysis_param_near_duplicate_minhash_v1",
      "status": "error",
      "reason": "killed_or_time_budget_exhausted",
      "duration_ms": 600147,
      "max_rss_kb": 0,
      "exit_code": -9,
      "priority_score": 1780147.0,
      "recommended_next_step": "Bound algorithmic complexity (pair checks, tokens, rows) and add deterministic caps.",
      "rank": 16
    },
    {
      "plugin_id": "analysis_param_near_duplicate_simhash_v1",
      "status": "error",
      "reason": "killed_or_time_budget_exhausted",
      "duration_ms": 600086,
      "max_rss_kb": 0,
      "exit_code": -9,
      "priority_score": 1780086.0,
      "recommended_next_step": "Bound algorithmic complexity (pair checks, tokens, rows) and add deterministic caps.",
      "rank": 17
    },
    {
      "plugin_id": "analysis_sparse_pca_interpretable_components_v1",
      "status": "ok",
      "reason": "high_memory_hotspot",
      "duration_ms": 77850,
      "max_rss_kb": 1637632,
      "exit_code": 0,
      "priority_score": 1775482.0,
      "recommended_next_step": "Stream/batch large computations and avoid materializing wide intermediate DataFrames.",
      "rank": 18
    },
    {
      "plugin_id": "analysis_changepoint_method_survey_guided",
      "status": "ok",
      "reason": "high_memory_hotspot",
      "duration_ms": 75761,
      "max_rss_kb": 1637540,
      "exit_code": 0,
      "priority_score": 1773301.0,
      "recommended_next_step": "Stream/batch large computations and avoid materializing wide intermediate DataFrames.",
      "rank": 19
    },
    {
      "plugin_id": "analysis_haar_wavelet_transient_detector_v1",
      "status": "ok",
      "reason": "high_memory_hotspot",
      "duration_ms": 58005,
      "max_rss_kb": 1642276,
      "exit_code": 0,
      "priority_score": 1760281.0,
      "recommended_next_step": "Stream/batch large computations and avoid materializing wide intermediate DataFrames.",
      "rank": 20
    },
    {
      "plugin_id": "analysis_circular_time_of_day_drift_v1",
      "status": "ok",
      "reason": "high_memory_hotspot",
      "duration_ms": 57186,
      "max_rss_kb": 1635824,
      "exit_code": 0,
      "priority_score": 1753010.0,
      "recommended_next_step": "Stream/batch large computations and avoid materializing wide intermediate DataFrames.",
      "rank": 21
    },
    {
      "plugin_id": "analysis_bayesian_online_changepoint_studentt_v1",
      "status": "ok",
      "reason": "high_memory_hotspot",
      "duration_ms": 63213,
      "max_rss_kb": 1629572,
      "exit_code": 0,
      "priority_score": 1752785.0,
      "recommended_next_step": "Stream/batch large computations and avoid materializing wide intermediate DataFrames.",
      "rank": 22
    },
    {
      "plugin_id": "analysis_distance_covariance_dependence_v1",
      "status": "ok",
      "reason": "high_memory_hotspot",
      "duration_ms": 55595,
      "max_rss_kb": 1636792,
      "exit_code": 0,
      "priority_score": 1752387.0,
      "recommended_next_step": "Stream/batch large computations and avoid materializing wide intermediate DataFrames.",
      "rank": 23
    },
    {
      "plugin_id": "analysis_quantile_sketch_p2_streaming_v1",
      "status": "ok",
      "reason": "high_memory_hotspot",
      "duration_ms": 55761,
      "max_rss_kb": 1633632,
      "exit_code": 0,
      "priority_score": 1749393.0,
      "recommended_next_step": "Stream/batch large computations and avoid materializing wide intermediate DataFrames.",
      "rank": 24
    },
    {
      "plugin_id": "analysis_state_space_smoother_level_shift_v1",
      "status": "ok",
      "reason": "high_memory_hotspot",
      "duration_ms": 48600,
      "max_rss_kb": 1637908,
      "exit_code": 0,
      "priority_score": 1746508.0,
      "recommended_next_step": "Stream/batch large computations and avoid materializing wide intermediate DataFrames.",
      "rank": 25
    },
    {
      "plugin_id": "analysis_beta_binomial_overdispersion_v1",
      "status": "ok",
      "reason": "high_memory_hotspot",
      "duration_ms": 48270,
      "max_rss_kb": 1638028,
      "exit_code": 0,
      "priority_score": 1746298.0,
      "recommended_next_step": "Stream/batch large computations and avoid materializing wide intermediate DataFrames.",
      "rank": 26
    },
    {
      "plugin_id": "analysis_mutual_information_screen",
      "status": "ok",
      "reason": "high_memory_hotspot",
      "duration_ms": 44365,
      "max_rss_kb": 1641368,
      "exit_code": 0,
      "priority_score": 1745733.0,
      "recommended_next_step": "Stream/batch large computations and avoid materializing wide intermediate DataFrames.",
      "rank": 27
    },
    {
      "plugin_id": "analysis_subspace_tracking_oja_v1",
      "status": "ok",
      "reason": "high_memory_hotspot",
      "duration_ms": 45572,
      "max_rss_kb": 1640060,
      "exit_code": 0,
      "priority_score": 1745632.0,
      "recommended_next_step": "Stream/batch large computations and avoid materializing wide intermediate DataFrames.",
      "rank": 28
    },
    {
      "plugin_id": "analysis_ssa_decomposition_changepoint_v1",
      "status": "ok",
      "reason": "high_memory_hotspot",
      "duration_ms": 67254,
      "max_rss_kb": 1618000,
      "exit_code": 0,
      "priority_score": 1745254.0,
      "recommended_next_step": "Stream/batch large computations and avoid materializing wide intermediate DataFrames.",
      "rank": 29
    },
    {
      "plugin_id": "analysis_stl_seasonal_decompose_v1",
      "status": "ok",
      "reason": "high_memory_hotspot",
      "duration_ms": 42392,
      "max_rss_kb": 1642700,
      "exit_code": 0,
      "priority_score": 1745092.0,
      "recommended_next_step": "Stream/batch large computations and avoid materializing wide intermediate DataFrames.",
      "rank": 30
    },
    {
      "plugin_id": "analysis_outlier_influence_cooks_distance_v1",
      "status": "ok",
      "reason": "high_memory_hotspot",
      "duration_ms": 46346,
      "max_rss_kb": 1638556,
      "exit_code": 0,
      "priority_score": 1744902.0,
      "recommended_next_step": "Stream/batch large computations and avoid materializing wide intermediate DataFrames.",
      "rank": 31
    },
    {
      "plugin_id": "analysis_spectral_radius_stability_v1",
      "status": "ok",
      "reason": "high_memory_hotspot",
      "duration_ms": 47140,
      "max_rss_kb": 1637076,
      "exit_code": 0,
      "priority_score": 1744216.0,
      "recommended_next_step": "Stream/batch large computations and avoid materializing wide intermediate DataFrames.",
      "rank": 32
    },
    {
      "plugin_id": "analysis_change_score_consensus_v1",
      "status": "ok",
      "reason": "high_memory_hotspot",
      "duration_ms": 47470,
      "max_rss_kb": 1636604,
      "exit_code": 0,
      "priority_score": 1744074.0,
      "recommended_next_step": "Stream/batch large computations and avoid materializing wide intermediate DataFrames.",
      "rank": 33
    },
    {
      "plugin_id": "analysis_bootstrap_ci_effect_sizes_v1",
      "status": "ok",
      "reason": "high_memory_hotspot",
      "duration_ms": 43466,
      "max_rss_kb": 1638880,
      "exit_code": 0,
      "priority_score": 1742346.0,
      "recommended_next_step": "Stream/batch large computations and avoid materializing wide intermediate DataFrames.",
      "rank": 34
    },
    {
      "plugin_id": "analysis_pca_auto",
      "status": "ok",
      "reason": "high_memory_hotspot",
      "duration_ms": 39850,
      "max_rss_kb": 1642128,
      "exit_code": 0,
      "priority_score": 1741978.0,
      "recommended_next_step": "Stream/batch large computations and avoid materializing wide intermediate DataFrames.",
      "rank": 35
    },
    {
      "plugin_id": "analysis_cca_crossblock_association_v1",
      "status": "ok",
      "reason": "high_memory_hotspot",
      "duration_ms": 45707,
      "max_rss_kb": 1636212,
      "exit_code": 0,
      "priority_score": 1741919.0,
      "recommended_next_step": "Stream/batch large computations and avoid materializing wide intermediate DataFrames.",
      "rank": 36
    },
    {
      "plugin_id": "analysis_random_matrix_marchenko_pastur_denoise_v1",
      "status": "ok",
      "reason": "high_memory_hotspot",
      "duration_ms": 43527,
      "max_rss_kb": 1637828,
      "exit_code": 0,
      "priority_score": 1741355.0,
      "recommended_next_step": "Stream/batch large computations and avoid materializing wide intermediate DataFrames.",
      "rank": 37
    },
    {
      "plugin_id": "analysis_chi_square_association",
      "status": "ok",
      "reason": "high_memory_hotspot",
      "duration_ms": 42236,
      "max_rss_kb": 1638756,
      "exit_code": 0,
      "priority_score": 1740992.0,
      "recommended_next_step": "Stream/batch large computations and avoid materializing wide intermediate DataFrames.",
      "rank": 38
    },
    {
      "plugin_id": "analysis_log_template_drain",
      "status": "ok",
      "reason": "high_memory_hotspot",
      "duration_ms": 37179,
      "max_rss_kb": 1643732,
      "exit_code": 0,
      "priority_score": 1740911.0,
      "recommended_next_step": "Stream/batch large computations and avoid materializing wide intermediate DataFrames.",
      "rank": 39
    },
    {
      "plugin_id": "analysis_quantile_loss_boosting_v1",
      "status": "ok",
      "reason": "high_memory_hotspot",
      "duration_ms": 41576,
      "max_rss_kb": 1639020,
      "exit_code": 0,
      "priority_score": 1740596.0,
      "recommended_next_step": "Stream/batch large computations and avoid materializing wide intermediate DataFrames.",
      "rank": 40
    }
  ]
}