{
  "generated_at": "2026-02-16T16:30:53.565903+00:00",
  "items": [
    {
      "avg_duration_ms": 12804.245901639344,
      "execution_count": 61,
      "max_rss_kb": 3040736.0,
      "plugin_id": "analysis_control_chart_suite",
      "plugin_type": "analysis",
      "priority_score": 2982.272995901639,
      "uses_dataset_loader_unbounded": true
    },
    {
      "avg_duration_ms": 11110.0,
      "execution_count": 54,
      "max_rss_kb": 2759176.0,
      "plugin_id": "analysis_distribution_drift_suite",
      "plugin_type": "analysis",
      "priority_score": 2705.6178125,
      "uses_dataset_loader_unbounded": true
    },
    {
      "avg_duration_ms": 10228.962264150943,
      "execution_count": 53,
      "max_rss_kb": 2698964.0,
      "plugin_id": "analysis_control_chart_cusum",
      "plugin_type": "analysis",
      "priority_score": 2645.935993514151,
      "uses_dataset_loader_unbounded": true
    },
    {
      "avg_duration_ms": 10223.74,
      "execution_count": 50,
      "max_rss_kb": 2697760.0,
      "plugin_id": "analysis_control_chart_individuals",
      "plugin_type": "analysis",
      "priority_score": 2644.75499,
      "uses_dataset_loader_unbounded": true
    },
    {
      "avg_duration_ms": 9319.923076923076,
      "execution_count": 52,
      "max_rss_kb": 2698380.0,
      "plugin_id": "analysis_control_chart_ewma",
      "plugin_type": "analysis",
      "priority_score": 2644.4566418269233,
      "uses_dataset_loader_unbounded": true
    },
    {
      "avg_duration_ms": 11281.24,
      "execution_count": 50,
      "max_rss_kb": 2627940.0,
      "plugin_id": "analysis_multivariate_control_charts",
      "plugin_type": "analysis",
      "priority_score": 2577.62889625,
      "uses_dataset_loader_unbounded": true
    },
    {
      "avg_duration_ms": 13504.375,
      "execution_count": 48,
      "max_rss_kb": 2494396.0,
      "plugin_id": "analysis_close_cycle_uplift",
      "plugin_type": "analysis",
      "priority_score": 2449.43796875,
      "uses_dataset_loader_unbounded": true
    },
    {
      "avg_duration_ms": 763546.3636363636,
      "execution_count": 11,
      "max_rss_kb": 1510568.0,
      "plugin_id": "analysis_change_score_consensus_v1",
      "plugin_type": "analysis",
      "priority_score": 2238.710426136364,
      "uses_dataset_loader_unbounded": true
    },
    {
      "avg_duration_ms": 13768.052631578947,
      "execution_count": 38,
      "max_rss_kb": 2277548.0,
      "plugin_id": "analysis_term_burst_kleinberg",
      "plugin_type": "analysis",
      "priority_score": 2237.936021381579,
      "uses_dataset_loader_unbounded": true
    },
    {
      "avg_duration_ms": 25049.089552238805,
      "execution_count": 67,
      "max_rss_kb": 2222632.0,
      "plugin_id": "analysis_actionable_ops_levers_v1",
      "plugin_type": "analysis",
      "priority_score": 2195.588152052239,
      "uses_dataset_loader_unbounded": true
    },
    {
      "avg_duration_ms": 604769.2857142857,
      "execution_count": 7,
      "max_rss_kb": 1521996.0,
      "plugin_id": "analysis_wild_binary_segmentation_v1",
      "plugin_type": "analysis",
      "priority_score": 2091.0935044642856,
      "uses_dataset_loader_unbounded": true
    },
    {
      "avg_duration_ms": 27559.0,
      "execution_count": 8,
      "max_rss_kb": 2049044.0,
      "plugin_id": "analysis_quantile_regression_forest_v1",
      "plugin_type": "analysis",
      "priority_score": 2028.57853125,
      "uses_dataset_loader_unbounded": true
    },
    {
      "avg_duration_ms": 9347.295454545454,
      "execution_count": 44,
      "max_rss_kb": 1947668.0,
      "plugin_id": "analysis_kernel_two_sample_mmd",
      "plugin_type": "analysis",
      "priority_score": 1911.3668267045455,
      "uses_dataset_loader_unbounded": true
    },
    {
      "avg_duration_ms": 18068.68181818182,
      "execution_count": 44,
      "max_rss_kb": 1922236.0,
      "plugin_id": "analysis_local_outlier_factor",
      "plugin_type": "analysis",
      "priority_score": 1895.2522755681819,
      "uses_dataset_loader_unbounded": true
    },
    {
      "avg_duration_ms": 10466.833333333334,
      "execution_count": 54,
      "max_rss_kb": 1923808.0,
      "plugin_id": "analysis_graph_topology_curves",
      "plugin_type": "analysis",
      "priority_score": 1889.1855833333334,
      "uses_dataset_loader_unbounded": true
    },
    {
      "avg_duration_ms": 11467.633333333333,
      "execution_count": 60,
      "max_rss_kb": 1896280.0,
      "plugin_id": "analysis_chi_square_association",
      "plugin_type": "analysis",
      "priority_score": 1863.3035708333334,
      "uses_dataset_loader_unbounded": true
    },
    {
      "avg_duration_ms": 27307.625,
      "execution_count": 8,
      "max_rss_kb": 1817944.0,
      "plugin_id": "analysis_poisson_regression_rate_drivers_v1",
      "plugin_type": "analysis",
      "priority_score": 1802.6435625,
      "uses_dataset_loader_unbounded": true
    },
    {
      "avg_duration_ms": 45656.181818181816,
      "execution_count": 11,
      "max_rss_kb": 1752248.0,
      "plugin_id": "analysis_beta_binomial_overdispersion_v1",
      "plugin_type": "analysis",
      "priority_score": 1756.8358693181817,
      "uses_dataset_loader_unbounded": true
    },
    {
      "avg_duration_ms": 48330.90909090909,
      "execution_count": 11,
      "max_rss_kb": 1740244.0,
      "plugin_id": "analysis_bootstrap_ci_effect_sizes_v1",
      "plugin_type": "analysis",
      "priority_score": 1747.787940340909,
      "uses_dataset_loader_unbounded": true
    },
    {
      "avg_duration_ms": 62853.72093023256,
      "execution_count": 43,
      "max_rss_kb": 1720328.0,
      "plugin_id": "analysis_markov_transition_shift",
      "plugin_type": "analysis",
      "priority_score": 1742.8615334302326,
      "uses_dataset_loader_unbounded": true
    }
  ],
  "schema_version": "streaming_offenders_ranked.v1",
  "top_n": 20,
  "total_candidates": 189
}
